{
    "348902662332481539": {
        "username": "anonymousserval",
        "elenco": {
            "2_16519": {
                "id_base": "2",
                "nivel": 1,
                "exp": 0
            }
        },
        "times": {},
        "moedas": {
            "pontos_espirito": 0,
            "relampagos_dourados": 0,
            "medalhas_raimon": 0
        }
    },
    "286332049738956801": {
        "username": "gbkuma",
        "elenco": {
            "2_35997": {
                "id_base": "2",
                "nivel": 1,
                "exp": 0
            }
        },
        "times": {},
        "moedas": {
            "pontos_espirito": 0,
            "relampagos_dourados": 0,
            "medalhas_raimon": 0
        }
    },
    "274233294525300740": {
        "username": "aoki_reika",
        "elenco": {},
        "times": {},
        "moedas": {
            "pontos_espirito": 0,
            "relampagos_dourados": 0,
            "medalhas_raimon": 0
        }
    },
    "667983352116019220": {
        "username": "kiitsun3_3",
        "elenco": {},
        "times": {},
        "moedas": {
            "pontos_espirito": 0,
            "relampagos_dourados": 0,
            "medalhas_raimon": 0
        }
    }
}